{
  "name": "Adelaide Glover",
  "age": 57,
  "address": {
    "street": "Osdak Key",
    "city": "Dargewopo",
    "state": "ND",
    "zip": "08538"
  },
  "contact": {
    "phone": "(374) 329-7402",
    "servicePhone": "800626191"
  },
  "birthday": "1972-05-04T16:56:03.460Z",
  "ip": "96.7.9.38",
  "foo": "bar",
  "profile": {
    "about": "Sehow lepo ti bu surow iv wu oruzo bawnenes funjog pul li idurinor avamonib zo kahud lawjisba atkobo. Bi we lol woenidi kifonom som sahowa nulzaic mamuw peban debkebu ikusechiv ciwom gi. Lom vutjad fitesket jewo keddeble mi netna reic tizapi nafid wacebi onahik. Hizul joowori emoroogo sobnetuk av fadwu ebamo ewtakir pihi feasi jujulhuv mi ip. Gifberne rokpaz zodga dezah jaido togjod tihjuj aso tounga ep ujcek adleun di me hodez uhki. Wij vet uphokzi peztemu johwe fo betik zo zogdinze pikzi vaf vuwvidza ewniwu. Kuhoit me neligsi nozseb mu usiwawkoj pib apakul ja sepeej dus ge soz cim lulfuz sa cut zopa.",
    "bio": "Zehaz jer to mectiz wega ji kole ovkigne edupehe itum owofevu uf polajo vaf ad hib waf zija. Lekfagow ripe mikehzub ripcupu fe wickuze lueme odu soekiw jatti jaajor onha rikeruc ucden ra luvgenah hegwi. Wik uludes bemcevcek wemu kowkizac debobamo baat mabreol robpu ne ve ejitezi nunrece vujda sowhi gokazves."
  },
  "apiKey": "3e4c746a82d5a623f05746532ba35462ecd947e6c98c9d223ad5628ebcea7d33",
  "currency": {
    "code": "LSL",
    "name": "Lesotho Loti"
  }
}