{
  "name": "Christina Gutierrez",
  "age": 27,
  "address": {
    "street": "Dizic Junction",
    "city": "Nilucu",
    "state": "PA",
    "zip": "29015"
  },
  "contact": {
    "phone": "(938) 623-9923",
    "servicePhone": "800168126"
  },
  "birthday": "1981-11-20T06:19:42.454Z",
  "ip": "142.15.41.141",
  "foo": "bar",
  "profile": {
    "about": "Vekna wohna uc zitapva jistuh jakukkuw gazficez fuc cul vu puvebho tafgagfol mob go pec nizmo. Huiwa emujej ladetnuh awiovifi vof to ci pefebane zo agjusag wu liflisgeg. Wem wam vekkocnuz ewe dar igizu ikebra hoj urnop sud lac fusaim wodi ze ew.",
    "bio": "Neoz mahufim hunap wehli viphamfil anewikav cado ino zisuwi jit sepitov zoc aci. Mewecil fekfa lujuh va monsu is su ketrizra sosjeeba ri oje iz je vuvcogor. Dowuvki negminda wigmit zus havwu cehdeina socemmi so zi vatnad mebalo udi nuveuj luwha el bo fihnoh upsanew. Fusofi pi ane jaim hugsaz bapveobo pagu cavasi kicaaw ri dedgi jo fivem loevu ledon."
  },
  "apiKey": "f4703ee5c93ead8a5e681aa22121dbfffb134cfb21b1af17b49a32a22e3752c7",
  "currency": {
    "code": "NOK",
    "name": "Norway Krone"
  }
}