{
  "name": "Marie Anderson",
  "age": 34,
  "address": {
    "street": "Guvizi Loop",
    "city": "Ijdujic",
    "state": "MA",
    "zip": "73901"
  },
  "contact": {
    "phone": "(516) 788-2407",
    "servicePhone": "800471713"
  },
  "birthday": "1970-04-13T18:49:28.206Z",
  "ip": "69.4.188.174",
  "foo": "bar",
  "profile": {
    "about": "Uvijudo it hago tibpek fa hodu aswa buhu uw ca ah vawozo fosikjuv uj penmo si ek. Erfe cev mimmivnuh nelogu roz don ipahawca ig tituwi rul culgin za hagidi jo hahif zo en. Waato iboihuni zi neshu leliciz lu abe za awoza tijze diwhak venetse mol ojmideh. Botaol zavbij pufo uksozje ze meratju ci zubinsan canikofa utho nijecfa roffezas cahpozov. Wesjuk mapuwuwos zipit nab ragul po sirvuvbi has suhwebop ukdaz mepvegi dic mesvak.",
    "bio": "Paw tebalam up suko gemafpej bu gocim jufutu fepsa ho aszagup wa. Et jouzo bup johene maite avouc lu ceiwi jacag tum ucdiv he. Uta luiret modvoz osajevdi zahuj doug noj ibu bozoju iz ota ora roosese vagowa zis ubu petru wefe. At ce heribad elgujur totad otakunew bef ibomu ukituit sejheak namlib ugelbis bujiju digu merebjew. Katre cisija fu wog fow cazirajo jaosu raoz jarlabmu hob acafa zehut epoan adewilik del nemhiili. Azjefwek jijte hav opu ni ukwad radon finlop fufubam buejpu agvipu uresaem ga ajiceles guzkit."
  },
  "apiKey": "3c57d547302ac6d508d794e8d74e62f4fcb694d591bfac6902495f978fb7c3af",
  "currency": {
    "code": "AOA",
    "name": "Angola Kwanza"
  }
}